setup.py
Offliberate/CLI.py
Offliberate/Offliberate.py
Offliberate/__init__.py
Offliberate.egg-info/PKG-INFO
Offliberate.egg-info/SOURCES.txt
Offliberate.egg-info/dependency_links.txt
Offliberate.egg-info/entry_points.txt
Offliberate.egg-info/requires.txt
Offliberate.egg-info/top_level.txt