Metadata-Version: 1.1
Name: Offliberate
Version: 1.1.1
Summary: Harness the power of Offliberty™ right from your terminal.
Home-page: https://github.com/PhilipTrauner/Offliberate
Author: Philip Trauner
Author-email: philip.trauner@aol.com
License: UNKNOWN
Keywords: youtube,offline,download,soundcloud,media,bandcamp,offliberty,offliberate
Platform: UNKNOWN
Classifier: Development Status :: 5 - Production/Stable
Classifier: Programming Language :: Python :: 3.4
Classifier: Programming Language :: Python :: 3.5
Classifier: Programming Language :: Python :: 3.6
Classifier: Intended Audience :: Developers
Classifier: Intended Audience :: End Users/Desktop
Classifier: License :: OSI Approved :: MIT License
